moolticutepy/__init__.py
moolticutepy/cli.py
moolticutepy/log.py
moolticutepy/moolticute_client.py
moolticutepy/schemas.py
moolticutepy-0.3.4.dist-info/LICENSE
moolticutepy-0.3.4.dist-info/METADATA
moolticutepy-0.3.4.dist-info/WHEEL
moolticutepy-0.3.4.dist-info/entry_points.txt
moolticutepy-0.3.4.dist-info/RECORD
