Metadata-Version: 2.1
Name: moolticutepy
Version: 0.3.4
Summary: Library an CLI to speak with moolticute service
License: LICENSE
Keywords: moolticute,moolticuted,mootlipass,mooltipassminible,mooltipassble,password,password manager
Author: Raul Sampedro
Author-email: 5142014+rsrdesarrollo@users.noreply.github.com
Requires-Python: >=3.12,<4.0
Classifier: License :: OSI Approved :: MIT License
Classifier: License :: Other/Proprietary License
Classifier: Programming Language :: Python
Classifier: Programming Language :: Python :: 3
Classifier: Programming Language :: Python :: 3.12
Classifier: Programming Language :: Python :: 3.13
Requires-Dist: click (>=8.1.7,<8.2.0)
Requires-Dist: pydantic (>=2.8.2,<2.9.0)
Requires-Dist: pydantic_core (>=2.20.1,<2.21.0)
Requires-Dist: websockets (>=13.0.1,<13.1.0)
Project-URL: Homepage, https://github.com/rsrdesarrollo/moolticutepy
